ansify/__init__.py
ansify/__main__.py
ansify/ansify.py
ansify/py.typed
ansify/settings.py
ansify-0.1.0.dist-info/entry_points.txt
ansify-0.1.0.dist-info/LICENSE
ansify-0.1.0.dist-info/WHEEL
ansify-0.1.0.dist-info/METADATA
ansify-0.1.0.dist-info/RECORD
