Metadata-Version: 2.1
Name: ansify
Version: 0.1.0
Summary: Awesome `ansify` is a Python CLI to create ANSI/ASCII art from images.
Home-page: https://github.com/lonsty/ansify
License: MIT
Author: lonsty
Author-email: lonsty@sina.com
Requires-Python: >=3.6.9,<4.0.0
Classifier: Development Status :: 3 - Alpha
Classifier: Intended Audience :: Developers
Classifier: License :: OSI Approved :: MIT License
Classifier: Operating System :: OS Independent
Classifier: Programming Language :: Python :: 3
Classifier: Programming Language :: Python :: 3.7
Classifier: Programming Language :: Python :: 3.8
Classifier: Programming Language :: Python :: 3.9
Classifier: Topic :: Software Development :: Libraries :: Python Modules
Requires-Dist: Pillow (>=8.1.2,<9.0.0)
Requires-Dist: importlib_metadata (>=1.6.0,<2.0.0); python_version < "3.8"
Requires-Dist: numpy (>=1.19.5,<2.0.0)
Requires-Dist: requests (>=2.25.1,<3.0.0)
Requires-Dist: rich (>=10.0.0,<11.0.0)
Requires-Dist: typer[all] (>=0.3.2,<0.4.0)
Requires-Dist: urwid (>=2.1.2,<3.0.0)
Project-URL: Repository, https://github.com/lonsty/ansify
